vortex/__init__.py
vortex/_lib.abi3.so
vortex/_lib/__init__.pyi
vortex/_lib/arrays.pyi
vortex/_lib/compress.pyi
vortex/_lib/dataset.pyi
vortex/_lib/dtype.pyi
vortex/_lib/expr.pyi
vortex/_lib/file.pyi
vortex/_lib/io.pyi
vortex/_lib/iter.pyi
vortex/_lib/registry.pyi
vortex/_lib/scalar.pyi
vortex/_lib/scan.pyi
vortex/_lib/serde.pyi
vortex/arrays.py
vortex/arrow/__init__.py
vortex/arrow/expression.py
vortex/dataset.py
vortex/expr.py
vortex/file.py
vortex/io.py
vortex/polars_.py
vortex/py.typed
vortex/ray/__init__.py
vortex/ray/datasource.py
vortex/registry.py
vortex/scan.py
vortex/serde.py
vortex/substrait.py
vortex/type_aliases.py
vortex_data-0.58.0.dist-info/METADATA
vortex_data-0.58.0.dist-info/WHEEL
vortex_data-0.58.0.dist-info/RECORD
