Metadata-Version: 2.4
Name: vortex-data
Version: 0.58.0
Classifier: Development Status :: 4 - Beta
Classifier: Intended Audience :: Developers
Classifier: Intended Audience :: Science/Research
Classifier: Programming Language :: Python :: 3
Classifier: Programming Language :: Python :: 3.11
Classifier: Programming Language :: Python :: 3.12
Classifier: Programming Language :: Python :: 3.13
Classifier: Programming Language :: Python :: 3.14
Classifier: License :: OSI Approved :: Apache Software License
Classifier: Topic :: Database
Classifier: Topic :: File Formats
Classifier: Topic :: Scientific/Engineering
Requires-Dist: pyarrow>=17.0.0
Requires-Dist: substrait>=0.23.0
Requires-Dist: typing-extensions>=4.5.0
Requires-Dist: polars>=1.31.0 ; extra == 'polars'
Requires-Dist: pandas>=2.2.0 ; extra == 'pandas'
Requires-Dist: numpy>=1.26.0 ; extra == 'numpy'
Requires-Dist: duckdb>=1.1.2 ; extra == 'duckdb'
Requires-Dist: ray>=2.48 ; extra == 'ray'
Provides-Extra: polars
Provides-Extra: pandas
Provides-Extra: numpy
Provides-Extra: duckdb
Provides-Extra: ray
Summary: Python bindings for Vortex, an Apache Arrow-compatible toolkit for working with compressed array data.
Home-Page: https://github.com/spiraldb/vortex
Author: Vortex Authors <hello@vortex.dev>
Author-email: Vortex Authors <hello@vortex.dev>
Requires-Python: >=3.11
Project-URL: Documentation, https://docs.vortex.dev
Project-URL: Changelog, https://github.com/vortex-data/vortex/blob/develop/CHANGELOG.md
Project-URL: Issues, https://github.com/vortex-data/vortex/issues
Project-URL: Benchmarks, https://bench.vortex.dev
